lingustruct/__init__.py
lingustruct/converters.py
lingustruct/core.py
lingustruct/license_manager.py
lingustruct/licensing.py
lingustruct/rate_limiter.py
lingustruct/security.py
lingustruct/templates.py
lingustruct/utils.py
lingustruct/validator.py
lingustruct/mappings/key_mapping.json
lingustruct/templates/m10_s.json
lingustruct/templates/m11_s.json
lingustruct/templates/m12_s.json
lingustruct/templates/m13_s.json
lingustruct/templates/m14_s.json
lingustruct/templates/m15_s.json
lingustruct/templates/m16_s.json
lingustruct/templates/m17_s.json
lingustruct/templates/m18_s.json
lingustruct/templates/m1_s.json
lingustruct/templates/m2_s.json
lingustruct/templates/m3_s.json
lingustruct/templates/m4_s.json
lingustruct/templates/m5_s.json
lingustruct/templates/m6_s.json
lingustruct/templates/m7_s.json
lingustruct/templates/m8_s.json
lingustruct/templates/m9_s.json
lingustruct/templates/master_template.json
lingustruct/templates/overview_template.json
lingustruct-0.3.10.dist-info/LICENSE
lingustruct-0.3.10.dist-info/METADATA
lingustruct-0.3.10.dist-info/WHEEL
lingustruct-0.3.10.dist-info/top_level.txt
lingustruct-0.3.10.dist-info/RECORD
