Metadata-Version: 2.1
Name: lingustruct
Version: 0.3.10
Summary: Framework for human and AI (LLM) collaboration in system design using LLM-optimized templates.
Home-page: https://pypi.org/project/lingustruct/
Author: Yasunori Abe
Author-email: osusume-co@lilseed.jp
License: Proprietary
Classifier: Programming Language :: Python :: 3
Classifier: License :: Other/Proprietary License
Classifier: Operating System :: OS Independent
Requires-Python: >=3.6
License-File: LICENSE
Requires-Dist: fastapi
Requires-Dist: uvicorn
Requires-Dist: jinja2
Requires-Dist: pydantic
Requires-Dist: weasyprint
Requires-Dist: markdown
Requires-Dist: openai
Requires-Dist: jsonschema
Requires-Dist: cryptography
Requires-Dist: requests
Requires-Dist: redis>=4.0.0
